{
    "blockly": false,
    "blockly_xml": "<xml></xml>",
    "category": "Uncategorized",
    "coa": {
        "data": {
            "description": "",
            "edges": [
                {
                    "id": "port_2_to_port_3",
                    "sourceNode": "2",
                    "sourcePort": "2_out",
                    "targetNode": "3",
                    "targetPort": "3_in"
                },
                {
                    "id": "port_0_to_port_4",
                    "sourceNode": "0",
                    "sourcePort": "0_out",
                    "targetNode": "4",
                    "targetPort": "4_in"
                },
                {
                    "id": "port_4_to_port_2",
                    "sourceNode": "4",
                    "sourcePort": "4_out",
                    "targetNode": "2",
                    "targetPort": "2_in"
                }
            ],
            "hash": "77d85f075a7b6af8d1601968f2975fc8e4b8df8e",
            "nodes": {
                "0": {
                    "data": {
                        "advanced": {
                            "join": []
                        },
                        "functionName": "on_start",
                        "id": "0",
                        "type": "start"
                    },
                    "errors": {},
                    "id": "0",
                    "type": "start",
                    "warnings": {
                        "context": [
                            "Connect block to playbook flow."
                        ]
                    },
                    "x": 1000,
                    "y": 279.9999999999999
                },
                "1": {
                    "data": {
                        "advanced": {
                            "join": []
                        },
                        "functionName": "on_finish",
                        "id": "1",
                        "type": "end"
                    },
                    "errors": {},
                    "id": "1",
                    "type": "end",
                    "warnings": {
                        "context": [
                            "Connect block to playbook flow."
                        ]
                    },
                    "x": 1000,
                    "y": 1000
                },
                "2": {
                    "data": {
                        "advanced": {
                            "customName": "format endpoint",
                            "customNameId": 0,
                            "join": []
                        },
                        "functionId": 1,
                        "functionName": "format_endpoint",
                        "id": "2",
                        "parameters": [
                            "playbook_input:collection_name",
                            "format_query:formatted_data"
                        ],
                        "template": "storage/collections/data/{0}?query=\"{1}\"\n",
                        "type": "format"
                    },
                    "errors": {},
                    "id": "2",
                    "type": "format",
                    "warnings": {},
                    "x": 980,
                    "y": 560
                },
                "3": {
                    "data": {
                        "action": "get data",
                        "actionType": "investigate",
                        "advanced": {
                            "join": []
                        },
                        "connector": "HTTP",
                        "connectorConfigs": [
                            "splunk no app"
                        ],
                        "connectorId": "290b7499-0374-4930-9cdc-5e9b05d65827",
                        "connectorVersion": "v1",
                        "functionId": 1,
                        "functionName": "get_data_1",
                        "id": "3",
                        "loop": {
                            "enabled": false,
                            "exitAfterUnit": "m",
                            "exitAfterValue": 10,
                            "exitConditionEnabled": false,
                            "exitLoopAfter": 2,
                            "pauseUnit": "m",
                            "pauseValue": 2
                        },
                        "parameters": {
                            "location": "format_endpoint:formatted_data"
                        },
                        "requiredParameters": [
                            {
                                "data_type": "string",
                                "field": "location"
                            }
                        ],
                        "type": "action"
                    },
                    "errors": {},
                    "id": "3",
                    "type": "action",
                    "warnings": {},
                    "x": 980,
                    "y": 700
                },
                "4": {
                    "data": {
                        "advanced": {
                            "customName": "format query",
                            "customNameId": 0,
                            "join": []
                        },
                        "functionId": 2,
                        "functionName": "format_query",
                        "id": "4",
                        "parameters": [],
                        "template": "{{\"url\":\"https://answerstedhctbek.onion\"}}\n",
                        "type": "format"
                    },
                    "errors": {},
                    "id": "4",
                    "type": "format",
                    "warnings": {},
                    "x": 980,
                    "y": 440
                }
            },
            "notes": ""
        },
        "input_spec": [
            {
                "contains": [],
                "description": "provide a collection name",
                "name": "collection_name"
            }
        ],
        "output_spec": null,
        "playbook_trigger": "artifact_created",
        "playbook_type": "data",
        "python_version": "3",
        "schema": "5.0.12",
        "version": "6.2.2.123"
    },
    "create_time": "2025-02-26T04:50:30.474463+00:00",
    "draft_mode": false,
    "labels": [
        "*"
    ],
    "tags": []
}